{
  "list": [
    {
      "Id": 1,
      "ncRecordId": "rec229b8601fc064",
      "ncRecordHash": "30f3e1c13747ff36570f1ab67eb99c64",
      "Date": "1",
      "RoomNumber": null,
      "CreatedAt": "2025-10-04 01:32:17+05:30",
      "UpdatedAt": "2025-10-04 01:32:17+05:30"
    },
    {
      "Id": 2,
      "ncRecordId": "rec4ff8471951854",
      "ncRecordHash": "44f0293f4c327bb84d5f5337530065f8",
      "Date": "2",
      "RoomNumber": null,
      "CreatedAt": "2025-10-04 01:32:17+05:30",
      "UpdatedAt": "2025-10-04 01:32:17+05:30"
    },
    {
      "Id": 3,
      "ncRecordId": "rec2e2f75ae2a794",
      "ncRecordHash": "d6c1a4bab0952958b7466f34f800da36",
      "Date": "3",
      "RoomNumber": "201 - 206",
      "CreatedAt": "2025-10-04 01:32:17+05:30",
      "UpdatedAt": "2025-10-04 01:32:17+05:30"
    },
    {
      "Id": 4,
      "ncRecordId": "rec93577ff9bc904",
      "ncRecordHash": "c5162e8934efcb7397933690bc2cc428",
      "Date": "4",
      "RoomNumber": "207 - 213",
      "CreatedAt": "2025-10-04 01:32:17+05:30",
      "UpdatedAt": "2025-10-04 01:32:17+05:30"
    },
    {
      "Id": 5,
      "ncRecordId": "recd3c99489c5644",
      "ncRecordHash": "9aa42bbe072dfbee4ffed534e6eefc4b",
      "Date": "5",
      "RoomNumber": null,
      "CreatedAt": "2025-10-04 01:32:17+05:30",
      "UpdatedAt": "2025-10-04 01:32:17+05:30"
    },
    {
      "Id": 6,
      "ncRecordId": "rec78af0fb7d55f4",
      "ncRecordHash": "b9b84fbecb32e9cf1995200ae15c9197",
      "Date": "6",
      "RoomNumber": "214 - 220",
      "CreatedAt": "2025-10-04 01:32:17+05:30",
      "UpdatedAt": "2025-10-04 01:32:17+05:30"
    },
    {
      "Id": 7,
      "ncRecordId": "rec60dc77ecf2634",
      "ncRecordHash": "9b037e204f34eb9e4c44bca4fa0fd422",
      "Date": "7",
      "RoomNumber": "221 - 229",
      "CreatedAt": "2025-10-04 01:32:17+05:30",
      "UpdatedAt": "2025-10-04 01:32:17+05:30"
    },
    {
      "Id": 8,
      "ncRecordId": "rec0ba8265dce8b4",
      "ncRecordHash": "5e65dcde010de4867d3e01c55bab8232",
      "Date": "8",
      "RoomNumber": "230 - 238",
      "CreatedAt": "2025-10-04 01:32:17+05:30",
      "UpdatedAt": "2025-10-04 01:32:17+05:30"
    },
    {
      "Id": 9,
      "ncRecordId": "reca01f04ca5cfc4",
      "ncRecordHash": "00bca87638bf5e5fdc181cc313d22052",
      "Date": "9",
      "RoomNumber": "239 - 250",
      "CreatedAt": "2025-10-04 01:32:17+05:30",
      "UpdatedAt": "2025-10-04 01:32:17+05:30"
    },
    {
      "Id": 10,
      "ncRecordId": "rec17cfed0b259c4",
      "ncRecordHash": "11d59c0f904b16efeb814ce83586c5f0",
      "Date": "10",
      "RoomNumber": "251 - 353",
      "CreatedAt": "2025-10-04 01:32:17+05:30",
      "UpdatedAt": "2025-10-04 01:32:17+05:30"
    },
    {
      "Id": 11,
      "ncRecordId": "recdc3ad49ee07b4",
      "ncRecordHash": "cec01d141c370eb63d0d9b8787ef0bf8",
      "Date": "11",
      "RoomNumber": "201 - 206",
      "CreatedAt": "2025-10-04 01:32:17+05:30",
      "UpdatedAt": "2025-10-04 01:32:17+05:30"
    },
    {
      "Id": 12,
      "ncRecordId": "recb09459d4604e4",
      "ncRecordHash": "0070a92a997f60feda48a3ccc71345f6",
      "Date": "12",
      "RoomNumber": null,
      "CreatedAt": "2025-10-04 01:32:17+05:30",
      "UpdatedAt": "2025-10-04 01:32:17+05:30"
    },
    {
      "Id": 13,
      "ncRecordId": "reccf9bcc2c26554",
      "ncRecordHash": "584124c07ec764bf3f59d07ff8da488b",
      "Date": "13",
      "RoomNumber": "207 - 213",
      "CreatedAt": "2025-10-04 01:32:17+05:30",
      "UpdatedAt": "2025-10-04 01:32:17+05:30"
    },
    {
      "Id": 14,
      "ncRecordId": "recec04c9fae21d4",
      "ncRecordHash": "b30bbdd8ccde83159f96f8e7c1f22ee6",
      "Date": "14",
      "RoomNumber": "214 - 220",
      "CreatedAt": "2025-10-04 01:32:17+05:30",
      "UpdatedAt": "2025-10-04 01:32:17+05:30"
    },
    {
      "Id": 15,
      "ncRecordId": "recefdf27792af94",
      "ncRecordHash": "3580c46f22d4209e1648bda27999370c",
      "Date": "15",
      "RoomNumber": "221 - 229",
      "CreatedAt": "2025-10-04 01:32:17+05:30",
      "UpdatedAt": "2025-10-04 01:32:17+05:30"
    },
    {
      "Id": 16,
      "ncRecordId": "rec32a07e0a089f4",
      "ncRecordHash": "30c256c1719a4cc663ddbeb3f563644c",
      "Date": "16",
      "RoomNumber": "230 - 238",
      "CreatedAt": "2025-10-04 01:32:17+05:30",
      "UpdatedAt": "2025-10-04 01:32:17+05:30"
    },
    {
      "Id": 17,
      "ncRecordId": "reced1abb59bc3d4",
      "ncRecordHash": "6cad65ef99ced071b84a61b9b823d4e4",
      "Date": "17",
      "RoomNumber": "239 - 250",
      "CreatedAt": "2025-10-04 01:32:17+05:30",
      "UpdatedAt": "2025-10-04 01:32:17+05:30"
    },
    {
      "Id": 18,
      "ncRecordId": "recd8a1e83080dd4",
      "ncRecordHash": "a6dcb8425f527df7f4bb0a0e5f9040c1",
      "Date": "18",
      "RoomNumber": "251 - 353",
      "CreatedAt": "2025-10-04 01:32:17+05:30",
      "UpdatedAt": "2025-10-04 01:32:17+05:30"
    },
    {
      "Id": 19,
      "ncRecordId": "rec27276bbf02824",
      "ncRecordHash": "2c66b5704b33d5da6c8ebac8203e3058",
      "Date": "19",
      "RoomNumber": null,
      "CreatedAt": "2025-10-04 01:32:17+05:30",
      "UpdatedAt": "2025-10-04 01:32:17+05:30"
    },
    {
      "Id": 20,
      "ncRecordId": "rec642f21f93b644",
      "ncRecordHash": "f3675e3ff01306098f7aa97bf8b8c2aa",
      "Date": "20",
      "RoomNumber": null,
      "CreatedAt": "2025-10-04 01:32:17+05:30",
      "UpdatedAt": "2025-10-04 01:32:17+05:30"
    },
    {
      "Id": 21,
      "ncRecordId": "rec6fdd2f60cff14",
      "ncRecordHash": "1e5b6565184d592eb77807a6b3e1c8c3",
      "Date": "21",
      "RoomNumber": null,
      "CreatedAt": "2025-10-04 01:32:17+05:30",
      "UpdatedAt": "2025-10-04 01:32:17+05:30"
    },
    {
      "Id": 22,
      "ncRecordId": "recaf0e04fef79f4",
      "ncRecordHash": "7fca32e7a62d172fe1171ee4894b1920",
      "Date": "22",
      "RoomNumber": "201 - 206",
      "CreatedAt": "2025-10-04 01:32:17+05:30",
      "UpdatedAt": "2025-10-04 01:32:17+05:30"
    },
    {
      "Id": 23,
      "ncRecordId": "recb051966cdde94",
      "ncRecordHash": "6463116fc7b9f72c1963c76521a3254c",
      "Date": "23",
      "RoomNumber": "207 - 213",
      "CreatedAt": "2025-10-04 01:32:17+05:30",
      "UpdatedAt": "2025-10-04 01:32:17+05:30"
    },
    {
      "Id": 24,
      "ncRecordId": "recb83080c47d8a4",
      "ncRecordHash": "2d5cdd8f9f4376b6a35052a831affd35",
      "Date": "24",
      "RoomNumber": "214 - 220",
      "CreatedAt": "2025-10-04 01:32:17+05:30",
      "UpdatedAt": "2025-10-04 01:32:17+05:30"
    },
    {
      "Id": 25,
      "ncRecordId": "rec4e3b3a9ca8bc4",
      "ncRecordHash": "79cb1c50cfca7ad1559f6f2fd2e10639",
      "Date": "25",
      "RoomNumber": "221 - 229",
      "CreatedAt": "2025-10-04 01:32:17+05:30",
      "UpdatedAt": "2025-10-04 01:32:17+05:30"
    },
    {
      "Id": 26,
      "ncRecordId": "rec4fcd578aafbe4",
      "ncRecordHash": "d2c3b67667e263484717e3241e1b0c6d",
      "Date": "26",
      "RoomNumber": null,
      "CreatedAt": "2025-10-04 01:32:17+05:30",
      "UpdatedAt": "2025-10-04 01:32:17+05:30"
    },
    {
      "Id": 27,
      "ncRecordId": "rec2c45570c681d4",
      "ncRecordHash": "6e88732da79b27f172650793d6dd1540",
      "Date": "27",
      "RoomNumber": "230 - 238",
      "CreatedAt": "2025-10-04 01:32:17+05:30",
      "UpdatedAt": "2025-10-04 01:32:17+05:30"
    },
    {
      "Id": 28,
      "ncRecordId": "rece500350489404",
      "ncRecordHash": "170d7a26514f386b3462ec9487bb3f94",
      "Date": "28",
      "RoomNumber": "239 - 250",
      "CreatedAt": "2025-10-04 01:32:17+05:30",
      "UpdatedAt": "2025-10-04 01:32:17+05:30"
    },
    {
      "Id": 29,
      "ncRecordId": "rec29fe18f8b57b4",
      "ncRecordHash": "2d599b7c4cc40dce70fae15cb89584f4",
      "Date": "29",
      "RoomNumber": "251 - 353",
      "CreatedAt": "2025-10-04 01:32:17+05:30",
      "UpdatedAt": "2025-10-04 01:32:17+05:30"
    },
    {
      "Id": 30,
      "ncRecordId": "reca9c23c9a9ab74",
      "ncRecordHash": "b4379cc2f938d9b29bfe9fa7d9eb24fb",
      "Date": "30",
      "RoomNumber": null,
      "CreatedAt": "2025-10-04 01:32:17+05:30",
      "UpdatedAt": "2025-10-04 01:32:17+05:30"
    },
    {
      "Id": 31,
      "ncRecordId": "rec8146642c21704",
      "ncRecordHash": "f7348589c8264f5c42e4e63bd622963e",
      "Date": "31",
      "RoomNumber": null,
      "CreatedAt": "2025-10-04 01:32:17+05:30",
      "UpdatedAt": "2025-10-04 01:32:17+05:30"
    }
  ],
  "pageInfo": {
    "totalRows": 31,
    "page": 1,
    "pageSize": 50,
    "isFirstPage": true,
    "isLastPage": true
  },
  "stats": {
    "dbQueryTime": "1.234"
  }
}