{
  "list": [
    {
      "Id": 1,
      "ncRecordId": "rec96b3c99e20c84",
      "ncRecordHash": "80bc773738a7d59847fc6d8a379e2a0a",
      "Day": "Monday",
      "Breakfast": "1. இட்லி, பருப்பு வடை, சாம்பார், புதினா சட்னி, பொடி, எண்ணெய்\n2. கீரையுடன் ஆம்லெட்\n3. பூரி, உருளைக்கிழங்கு மசாலா (பட்டாணி & கேரட் சேர்க்கப்பட்டது)\n4. தேநீர், பால், காபி\n5. ரொட்டி, வெண்ணெய், ஜாம்",
      "Lunch": "1. ஃபுல்கா, சோயா கிரேவி\n2. பச்சை பீன்ஸ் உடன் தக்காளி சாதம்\n3. வெள்ளை சாதம், முள்ளங்கி சாம்பார் (கூடுதல் முருங்கைக்காய்), ரசம், வாழைக்காய் புட்டு பொரியல், தயிர்\n4. பருப்பு பொடி, நெய், துவையல், ஊறுகாய், அப்பளம்\n5. பழம் - அன்னாசி, எலுமிச்சை புதினா ஜூஸ்",
      "Snacks": "1. வெள்ளை பாஸ்தா / வெஜ் சமோசா பச்சை சட்னி \n2. தேநீர், காபி, பால்",
      "Dinner": "1. சப்பாத்தி, செட்டிநாடு முட்டை மசாலா\n2. பருப்பு தம்\n3. வெள்ளை சாதம், ரசம், வறுத்த வெண்டைக்காய் பொரியல், மோர்\n4. சாலட் (கேரட், வெள்ளரி, தக்காளி)\n5. ஐஸ்கிரீம், பால்",
      "CreatedAt": "2025-09-11 20:25:53+05:30",
      "UpdatedAt": "2025-09-11 20:25:53+05:30"
    },
    {
      "Id": 2,
      "ncRecordId": "rec36f1112228ff4",
      "ncRecordHash": "ff0e951363351960f9cb47e3d48a9d2f",
      "Day": "Tuesday",
      "Breakfast": "1. பன்னீர் பராத்தா, தக்காளி வெங்காய கிரேவி, தயிர்\n2. நெய் பொங்கல், வடை, காய்கறி சாம்பார், தேங்காய் சட்னி\n3. அவித்த முட்டை\n4. தேநீர், பால், காபி\n5. ரொட்டி, வெண்ணெய், ஜாம்",
      "Lunch": "1. சப்பாத்தி, பச்சை பட்டாணி மசாலா / குடைமிளகாய் உடன் பன்னீர் பட்டர் மசாலா \n2. புதினா சாதம் / தேங்காய் சாதம்\n3. வெள்ளை சாதம், மோர் குழம்பு, மிளகு ரசம், கேரட் பீன்ஸ் பொரியல், தயிர்\n4. பாயசம், எலுமிச்சை புதினா ஜூஸ்",
      "Snacks": "1. மசாலாவுடன் அவித்த இனிப்பு சோளம்\n2. தேநீர், காபி, பால்",
      "Dinner": "1. ஃபுல்கா, பாலக் கோஃப்தா கறி\n2. அடை தோசை, தக்காளி வெங்காய சட்னி, சாம்பார்\n3. வெள்ளை சாதம், கருப்பு பருப்பு, ரசம், முட்டைக்கோஸ் பொரியல், மோர்\n4. சாலட் (கேரட், பீட்ரூட், வெள்ளரி)\n5. பால்\n6. வாழைப்பழம்",
      "CreatedAt": "2025-09-11 20:25:53+05:30",
      "UpdatedAt": "2025-09-11 20:25:53+05:30"
    },
    {
      "Id": 3,
      "ncRecordId": "rec4f15c0dac0574",
      "ncRecordHash": "a10763aa65b32bd76f206c8d2415e13a",
      "Day": "Wednesday",
      "Breakfast": "1. மெல்லிய தோசை, வடைக்கறி, வெங்காய சட்னி\n2. வெஜ் கிச்சடி\n3. வெங்காயம் மற்றும் தக்காளி உடன் முட்டை புர்ஜி\n4. தேநீர், பால், காபி\n5. ரொட்டி, வெண்ணெய், ஜாம்",
      "Lunch": "1. ஓமம் சப்பாத்தி, டிராகன் சிக்கன் / தந்தூரி சிக்கன்\n2. வெஜ் புலாவ் (கூடுதல் பீன்ஸ், கேரட்) / சீரக சாதம்\n3. வெள்ளை சாதம், கலவை, வெஜ் பருப்பு, ரசம், கொத்தவரங்காய் பொரியல், தயிர்\n4. பருப்பு பொடி, நல்லெண்ணெய், துவையல், ஊறுகாய், அப்பளம்\n5. நன்னாரி ஜூஸ்",
      "Snacks": "1. பானி பூரி  / தஹி பூரி \n2. தேநீர், காபி, பால்",
      "Dinner": "1. ரோட்டி, காளான் மசாலா\n2. காலிஃபிளவர் & பீன்ஸ் உடன் வெஜ் பிரியாணி, ராய்தா\n3. வெள்ளை சாதம், ரசம், பிரெஞ்சு பிரைஸ், மோர்\n4. பழ கஸ்டர்ட்\n5. பால்",
      "CreatedAt": "2025-09-11 20:25:53+05:30",
      "UpdatedAt": "2025-09-11 20:25:53+05:30"
    },
    {
      "Id": 4,
      "ncRecordId": "rec40a0727cd4fc4",
      "ncRecordHash": "3b092b6b79fbed15d579d4f49b254ce4",
      "Day": "Thursday",
      "Breakfast": "1. பாவ் பாஜி (கூடுதல் முட்டைக்கோஸ் & பீன்ஸ்), மசாலா, நறுக்கிய வெங்காயம் மற்றும் மிளகாய்\n2. கேரட் தோசை, வேர்க்கடலை சட்னி, சாம்பார்\n3. பிரெஞ்சு டோஸ்ட்\n4. தேநீர், பால், காபி\n5. ரொட்டி, வெண்ணெய், ஜாம்",
      "Lunch": "1. ஃபுல்கா, கீரையுடன் தால் மக்கானி\n2. பீன்ஸ், கேரட் & முருங்கைக்காய் உடன் பிசிபேளாபாத் \n3. வெள்ளை சாதம், காராமணி கார புளி குழம்பு, ரசம், வறுத்த கீரை பொரியல், தயிர்\n4. பருப்பு பொடி, நெய், துவையல், ஊறுகாய், உருளைக்கிழங்கு சிப்ஸ்\n5. ஜல் ஜீரா, பழம் - தர்பூசணி",
      "Snacks": "1. வாழைக்காய் பஜ்ஜி / வெங்காய பக்கோடா \n2. தேநீர், காபி, பால்",
      "Dinner": "1. ஃபுல்கா, முட்டை கிரேவி\n2. மசாலா தோசை, கேரட் சட்னி, சாம்பார்\n3. வெள்ளை சாதம், பருப்பு, ரசம், வறுத்த கருணைக்கிழங்கு வறுவல், மோர்\n4. சாலட்\n5. பால், ஜிலேபி",
      "CreatedAt": "2025-09-11 20:25:53+05:30",
      "UpdatedAt": "2025-09-11 20:25:53+05:30"
    },
    {
      "Id": 5,
      "ncRecordId": "rec73102fd6cf8c4",
      "ncRecordHash": "738230889091dfda1244041b8fc78b0b",
      "Day": "Friday",
      "Breakfast": "1. இடியாப்பம், தேங்காய் பால், வெஜ் ஸ்டூ (கூடுதல் கேரட் & பீன்ஸ்)\n2. உருளைக்கிழங்கு போஹா, வெங்காயம் / ஆலு பராத்தா, தயிர், ஊறுகாய்\n3. அவித்த முட்டை\n4. தேநீர், பால், காபி\n5. கோதுமை ரொட்டி, வெண்ணெய், ஜாம்",
      "Lunch": "1. ஃபுல்கா, பன்னீர் டிக்கா மசாலா\n2. புளி சாதம்  / மாங்காய் சாதம்\n3. வெள்ளை சாதம், முருங்கைக்காய் சாம்பார், புடலங்காய் பொரியல், ரசம், தயிர்\n4. பருப்பு பொடி, நெய், பருப்பு துவையல், ஊறுகாய், அப்பளம், பழ சாலட்\n5. எலுமிச்சை புதினா ஜூஸ்",
      "Snacks": "1. சாம்பார் வடை (கூடுதல் காய்கறிகள்) / தனி காய்கறிகளுடன் பேல் பூரி \n2. தேநீர், காபி, பால்",
      "Dinner": "1. கோதுமை பராத்தா, செட்டிநாடு சிக்கன் கிரேவி / கடாய் சிக்கன் கிரேவி \n2. இட்லி, தக்காளி வெஜ் குருமா, சட்னி\n3. வெள்ளை சாதம், ரசம், மோர்\n4. குலாப் ஜாமுன்\n5. சாலட்\n6. சாக்லேட் பால் / பாதாம் பால் ",
      "CreatedAt": "2025-09-11 20:25:53+05:30",
      "UpdatedAt": "2025-09-11 20:25:53+05:30"
    },
    {
      "Id": 6,
      "ncRecordId": "recee6b2d8b55624",
      "ncRecordHash": "75b62dbe099e1991cf82b07ff1380739",
      "Day": "Saturday",
      "Breakfast": "1. வெள்ளை புட்டு, கடலை கறி, துருவிய தேங்காய், வாழைப்பழம், சர்க்கரை + நெய்\n2. வெஜ் பராத்தா, தயிர், ஊறுகாய்\n3. அவித்த முட்டை\n4. தேநீர், பால், காபி\n5. ரொட்டி, வெண்ணெய், ஜாம்",
      "Lunch": "1. பாலக் சப்பாத்தி, தால் பஞ்சாபி\n2. குடைமிளகாய் உடன் முட்டை வறுத்த சாதம், முட்டைக்கோஸ் மற்றும் பீன்ஸ் உடன் வெஜ் மஞ்சூரியன்\n3. வெள்ளை சாதம், பச்சை பருப்பு கறி, பீட்ரூட் பொரியல், ரசம், தயிர்\n4. பருப்பு பொடி, நெய், துவையல், ஊறுகாய், அப்பளம்\n5. எலுமிச்சை ஜூஸ்",
      "Snacks": "1. சுண்டல் (துருவிய தேங்காயுடன்) / சன்னா சாட் (வெள்ளரி, வெங்காயம், கேரட்) \n2. தேநீர், காபி, பால்",
      "Dinner": "1. சப்பாத்தி, ஆலு தம் கிரேவி / ஆலு பட்டாணி கிரேவி / சோலே பத்தூரே, வெள்ளை கொண்டைக்கடலை மசாலா, மிர்ச்சி ராய்தா\n2. வெஜ் சேமியா / தக்காளி சேமியா, சட்னி\n3. வெள்ளை சாதம், பருப்பு, ரசம், கோபி 65, மோர்\n4. சாலட் (கேரட், பீட்ரூட், வெள்ளரி)\n5. பால் ",
      "CreatedAt": "2025-09-11 20:25:53+05:30",
      "UpdatedAt": "2025-09-11 20:25:53+05:30"
    },
    {
      "Id": 7,
      "ncRecordId": "recf69ee738a7b24",
      "ncRecordHash": "04d8a1e035038a643f07be8dd9f602e1",
      "Day": "Sunday",
      "Breakfast": "1. பொடி வெங்காய ஊத்தப்பம், சாம்பார், சட்னி\n2. கேரட் மற்றும் பீன்ஸ் உடன் சபுதானா கிச்சடி\n3. தேநீர், பால், காபி\n4. ரொட்டி, வெண்ணெய், ஜாம்",
      "Lunch": "1. செட்டிநாடு சிக்கன் பிரியாணி  / ஹைதராபாத் தம் சிக்கன் பிரியாணி \n2. துண்டுகள் இல்லாத சிக்கன் கிரேவி, வெங்காய ராய்தா, கத்திரிக்காய் கறி, அவித்த முட்டை, கோபி 65\n3. ஃபுல்கா, கருப்பு கொண்டைக்கடலை தால் கறி\n4. வெள்ளை சாதம், ரசம், தயிர் சாதம், ஊறுகாய்\n5. பிரட் அல்வா, எலுமிச்சை புதினா ஜூஸ்",
      "Snacks": "1. பர்கர் (பேட்டி, தக்காளி, வெள்ளரி) சாஸ் / கச்சோடி, கார சட்னி \n2. தேநீர், காபி, பால்",
      "Dinner": "1. ஃபுல்கா, ராஜ்மா கறி\n2. மேத்தி புலாவ்\n3. வெள்ளை சாதம், சாம்பார் பூசணி, தக்காளி ரசம், கேரட் பொரியல் \n4. மோர், அப்பளம்\n5. பழம் - பப்பாளி",
      "CreatedAt": "2025-09-11 20:25:53+05:30",
      "UpdatedAt": "2025-09-11 20:25:53+05:30"
    }
  ],
  "pageInfo": {
    "totalRows": 7,
    "page": 1,
    "pageSize": 50,
    "isFirstPage": true,
    "isLastPage": true
  },
  "stats": {
    "dbQueryTime": "1.234"
  }
}